timing/__init__.py
timing/main.py
slimebones_timing-0.1.0.dist-info/LICENSE
slimebones_timing-0.1.0.dist-info/METADATA
slimebones_timing-0.1.0.dist-info/WHEEL
slimebones_timing-0.1.0.dist-info/entry_points.txt
slimebones_timing-0.1.0.dist-info/RECORD
